{"features": [{"geometry": {"coordinates": [[7460.0, -1360.0], [7460.0, -1360.0]], "type": "LineString"}, "id": 505, "properties": {"stroke-width": 1}, "type": "Feature"}, {"geometry": {"coordinates": [[7460.0, -1360.0], [7460.0, -1350.0]], "type": "LineString"}, "id": 506, "properties": {"stroke-width": 1}, "type": "Feature"}, {"geometry": {"coordinates": [[7460.0, -1350.0], [7470.0, -1350.0]], "type": "LineString"}, "id": 507, "properties": {"stroke-width": 1}, "type": "Feature"}, {"geometry": {"coordinates": [[7470.0, -1350.0], [7470.0, -1350.0]], "type": "LineString"}, "id": 508, "properties": {"stroke-width": 1}, "type": "Feature"}, {"geometry": {"coordinates": [[8180.0, -1550.0], [8180.0, -1550.0]], "type": "LineString"}, "id": 883, "properties": {"stroke-width": 1}, "type": "Feature"}, {"geometry": {"coordinates": [[8180.0, -1550.0], [8180.0, -1540.0]], "type": "LineString"}, "id": 884, "properties": {"stroke-width": 1}, "type": "Feature"}, {"geometry": {"coordinates": [[8180.0, -1540.0], [8170.0, -1540.0]], "type": "LineString"}, "id": 885, "properties": {"stroke-width": 1}, "type": "Feature"}, {"geometry": {"coordinates": [[8170.0, -1540.0], [8160.0, -1540.0]], "type": "LineString"}, "id": 886, "properties": {"stroke-width": 1}, "type": "Feature"}, {"geometry": {"coordinates": [[8160.0, -1540.0], [8150.0, -1540.0]], "type": "LineString"}, "id": 887, "properties": {"stroke-width": 1}, "type": "Feature"}, {"geometry": {"coordinates": [[8150.0, -1540.0], [8150.0, -1550.0]], "type": "LineString"}, "id": 888, "properties": {"stroke-width": 1}, "type": "Feature"}, {"geometry": {"coordinates": [[8150.0, -1550.0], [8150.0, -1560.0]], "type": "LineString"}, "id": 889, "properties": {"stroke-width": 1}, "type": "Feature"}, {"geometry": {"coordinates": [[8150.0, -1560.0], [8150.0, -1570.0]], "type": "LineString"}, "id": 890, "properties": {"stroke-width": 1}, "type": "Feature"}, {"geometry": {"coordinates": [[8150.0, -1570.0], [8150.0, -1580.0]], "type": "LineString"}, "id": 891, "properties": {"stroke-width": 1}, "type": "Feature"}, {"geometry": {"coordinates": [[8150.0, -1580.0], [8150.0, -1580.0]], "type": "LineString"}, "id": 892, "properties": {"stroke-width": 1}, "type": "Feature"}, {"geometry": {"coordinates": [[8120.0, -1640.0], [8120.0, -1640.0]], "type": "LineString"}, "id": 908, "properties": {"stroke-width": 1}, "type": "Feature"}, {"geometry": {"coordinates": [[8120.0, -1640.0], [8120.0, -1640.0]], "type": "LineString"}, "id": 909, "properties": {"stroke-width": 1}, "type": "Feature"}, {"geometry": {"coordinates": [[6360.0, -1660.0], [6360.0, -1660.0]], "type": "LineString"}, "id": 1222, "properties": {"stroke-width": 1}, "type": "Feature"}, {"geometry": {"coordinates": [[6360.0, -1660.0], [6350.0, -1660.0]], "type": "LineString"}, "id": 1223, "properties": {"stroke-width": 1}, "type": "Feature"}, {"geometry": {"coordinates": [[6350.0, -1660.0], [6340.0, -1660.0]], "type": "LineString"}, "id": 1224, "properties": {"stroke-width": 1}, "type": "Feature"}, {"geometry": {"coordinates": [[6340.0, -1660.0], [6340.0, -1660.0]], "type": "LineString"}, "id": 1225, "properties": {"stroke-width": 1}, "type": "Feature"}, {"geometry": {"coordinates": [[7030.0, -2970.0], [7030.0, -2970.0]], "type": "LineString"}, "id": 1560, "properties": {"stroke-width": 1}, "type": "Feature"}, {"geometry": {"coordinates": [[7030.0, -2970.0], [7040.0, -2970.0]], "type": "LineString"}, "id": 1561, "properties": {"stroke-width": 1}, "type": "Feature"}, {"geometry": {"coordinates": [[7040.0, -2970.0], [7040.0, -2980.0]], "type": "LineString"}, "id": 1562, "properties": {"stroke-width": 1}, "type": "Feature"}, {"geometry": {"coordinates": [[7040.0, -2980.0], [7040.0, -2990.0]], "type": "LineString"}, "id": 1563, "properties": {"stroke-width": 1}, "type": "Feature"}, {"geometry": {"coordinates": [[7130.0, -3060.0], [7130.0, -3060.0]], "type": "LineString"}, "id": 1583, "properties": {"stroke-width": 1}, "type": "Feature"}, {"geometry": {"coordinates": [[7130.0, -3060.0], [7130.0, -3070.0]], "type": "LineString"}, "id": 1584, "properties": {"stroke-width": 1}, "type": "Feature"}, {"geometry": {"coordinates": [[7130.0, -3070.0], [7130.0, -3080.0]], "type": "LineString"}, "id": 1585, "properties": {"stroke-width": 1}, "type": "Feature"}, {"geometry": {"coordinates": [[7130.0, -3080.0], [7130.0, -3090.0]], "type": "LineString"}, "id": 1586, "properties": {"stroke-width": 1}, "type": "Feature"}, {"geometry": {"coordinates": [[7130.0, -3090.0], [7130.0, -3100.0]], "type": "LineString"}, "id": 1587, "properties": {"stroke-width": 1}, "type": "Feature"}, {"geometry": {"coordinates": [[7130.0, -3100.0], [7140.0, -3100.0]], "type": "LineString"}, "id": 1588, "properties": {"stroke-width": 1}, "type": "Feature"}, {"geometry": {"coordinates": [[7140.0, -3100.0], [7150.0, -3100.0]], "type": "LineString"}, "id": 1589, "properties": {"stroke-width": 1}, "type": "Feature"}, {"geometry": {"coordinates": [[7150.0, -3100.0], [7150.0, -3110.0]], "type": "LineString"}, "id": 1590, "properties": {"stroke-width": 1}, "type": "Feature"}, {"geometry": {"coordinates": [[7150.0, -3110.0], [7160.0, -3110.0]], "type": "LineString"}, "id": 1591, "properties": {"stroke-width": 1}, "type": "Feature"}, {"geometry": {"coordinates": [[7160.0, -3110.0], [7170.0, -3110.0]], "type": "LineString"}, "id": 1592, "properties": {"stroke-width": 1}, "type": "Feature"}, {"geometry": {"coordinates": [[7170.0, -3110.0], [7170.0, -3120.0]], "type": "LineString"}, "id": 1593, "properties": {"stroke-width": 1}, "type": "Feature"}, {"geometry": {"coordinates": [[7170.0, -3120.0], [7170.0, -3130.0]], "type": "LineString"}, "id": 1594, "properties": {"stroke-width": 1}, "type": "Feature"}, {"geometry": {"coordinates": [[7170.0, -3130.0], [7170.0, -3140.0]], "type": "LineString"}, "id": 1595, "properties": {"stroke-width": 1}, "type": "Feature"}, {"geometry": {"coordinates": [[7170.0, -3140.0], [7180.0, -3140.0]], "type": "LineString"}, "id": 1596, "properties": {"stroke-width": 1}, "type": "Feature"}, {"geometry": {"coordinates": [[7180.0, -3140.0], [7180.0, -3150.0]], "type": "LineString"}, "id": 1597, "properties": {"stroke-width": 1}, "type": "Feature"}, {"geometry": {"coordinates": [[7180.0, -3150.0], [7180.0, -3160.0]], "type": "LineString"}, "id": 1598, "properties": {"stroke-width": 1}, "type": "Feature"}, {"geometry": {"coordinates": [[7180.0, -3160.0], [7190.0, -3160.0]], "type": "LineString"}, "id": 1599, "properties": {"stroke-width": 1}, "type": "Feature"}, {"geometry": {"coordinates": [[7190.0, -3160.0], [7190.0, -3170.0]], "type": "LineString"}, "id": 1600, "properties": {"stroke-width": 1}, "type": "Feature"}, {"geometry": {"coordinates": [[7190.0, -3170.0], [7200.0, -3170.0]], "type": "LineString"}, "id": 1601, "properties": {"stroke-width": 1}, "type": "Feature"}, {"geometry": {"coordinates": [[7200.0, -3170.0], [7200.0, -3180.0]], "type": "LineString"}, "id": 1602, "properties": {"stroke-width": 1}, "type": "Feature"}, {"geometry": {"coordinates": [[7200.0, -3180.0], [7200.0, -3190.0]], "type": "LineString"}, "id": 1603, "properties": {"stroke-width": 1}, "type": "Feature"}, {"geometry": {"coordinates": [[7200.0, -3190.0], [7200.0, -3200.0]], "type": "LineString"}, "id": 1604, "properties": {"stroke-width": 1}, "type": "Feature"}, {"geometry": {"coordinates": [[7200.0, -3200.0], [7200.0, -3210.0]], "type": "LineString"}, "id": 1605, "properties": {"stroke-width": 1}, "type": "Feature"}, {"geometry": {"coordinates": [[7200.0, -3210.0], [7200.0, -3220.0]], "type": "LineString"}, "id": 1606, "properties": {"stroke-width": 1}, "type": "Feature"}, {"geometry": {"coordinates": [[7200.0, -3220.0], [7210.0, -3220.0]], "type": "LineString"}, "id": 1607, "properties": {"stroke-width": 1}, "type": "Feature"}, {"geometry": {"coordinates": [[7210.0, -3220.0], [7210.0, -3230.0]], "type": "LineString"}, "id": 1608, "properties": {"stroke-width": 1}, "type": "Feature"}, {"geometry": {"coordinates": [[7210.0, -3230.0], [7210.0, -3240.0]], "type": "LineString"}, "id": 1609, "properties": {"stroke-width": 1}, "type": "Feature"}, {"geometry": {"coordinates": [[7210.0, -3240.0], [7210.0, -3250.0]], "type": "LineString"}, "id": 1610, "properties": {"stroke-width": 1}, "type": "Feature"}, {"geometry": {"coordinates": [[7210.0, -3250.0], [7210.0, -3260.0]], "type": "LineString"}, "id": 1611, "properties": {"stroke-width": 1}, "type": "Feature"}, {"geometry": {"coordinates": [[7210.0, -3260.0], [7210.0, -3270.0]], "type": "LineString"}, "id": 1612, "properties": {"stroke-width": 1}, "type": "Feature"}, {"geometry": {"coordinates": [[7210.0, -3270.0], [7210.0, -3280.0]], "type": "LineString"}, "id": 1613, "properties": {"stroke-width": 1}, "type": "Feature"}, {"geometry": {"coordinates": [[7210.0, -3280.0], [7220.0, -3280.0]], "type": "LineString"}, "id": 1614, "properties": {"stroke-width": 1}, "type": "Feature"}, {"geometry": {"coordinates": [[7220.0, -3280.0], [7220.0, -3280.0]], "type": "LineString"}, "id": 1615, "properties": {"stroke-width": 1}, "type": "Feature"}, {"geometry": {"coordinates": [[7250.0, -2970.0], [7250.0, -2970.0]], "type": "LineString"}, "id": 1875, "properties": {"stroke-width": 1}, "type": "Feature"}, {"geometry": {"coordinates": [[7250.0, -2970.0], [7250.0, -2980.0]], "type": "LineString"}, "id": 1876, "properties": {"stroke-width": 1}, "type": "Feature"}, {"geometry": {"coordinates": [[7250.0, -2980.0], [7250.0, -2990.0]], "type": "LineString"}, "id": 1877, "properties": {"stroke-width": 1}, "type": "Feature"}, {"geometry": {"coordinates": [[7250.0, -2990.0], [7250.0, -3000.0]], "type": "LineString"}, "id": 1878, "properties": {"stroke-width": 1}, "type": "Feature"}, {"geometry": {"coordinates": [[7250.0, -3000.0], [7250.0, -3010.0]], "type": "LineString"}, "id": 1879, "properties": {"stroke-width": 1}, "type": "Feature"}, {"geometry": {"coordinates": [[7250.0, -3010.0], [7250.0, -3020.0]], "type": "LineString"}, "id": 1880, "properties": {"stroke-width": 1}, "type": "Feature"}, {"geometry": {"coordinates": [[7250.0, -3020.0], [7250.0, -3030.0]], "type": "LineString"}, "id": 1881, "properties": {"stroke-width": 1}, "type": "Feature"}, {"geometry": {"coordinates": [[7250.0, -3030.0], [7250.0, -3040.0]], "type": "LineString"}, "id": 1882, "properties": {"stroke-width": 1}, "type": "Feature"}, {"geometry": {"coordinates": [[7250.0, -3040.0], [7250.0, -3050.0]], "type": "LineString"}, "id": 1883, "properties": {"stroke-width": 1}, "type": "Feature"}, {"geometry": {"coordinates": [[7250.0, -3050.0], [7250.0, -3060.0]], "type": "LineString"}, "id": 1884, "properties": {"stroke-width": 1}, "type": "Feature"}, {"geometry": {"coordinates": [[7250.0, -3060.0], [7250.0, -3070.0]], "type": "LineString"}, "id": 1885, "properties": {"stroke-width": 1}, "type": "Feature"}, {"geometry": {"coordinates": [[7250.0, -3070.0], [7250.0, -3080.0]], "type": "LineString"}, "id": 1886, "properties": {"stroke-width": 1}, "type": "Feature"}, {"geometry": {"coordinates": [[7250.0, -3080.0], [7250.0, -3090.0]], "type": "LineString"}, "id": 1887, "properties": {"stroke-width": 1}, "type": "Feature"}, {"geometry": {"coordinates": [[7250.0, -3090.0], [7250.0, -3100.0]], "type": "LineString"}, "id": 1888, "properties": {"stroke-width": 1}, "type": "Feature"}, {"geometry": {"coordinates": [[7250.0, -3100.0], [7260.0, -3100.0]], "type": "LineString"}, "id": 1889, "properties": {"stroke-width": 1}, "type": "Feature"}, {"geometry": {"coordinates": [[7260.0, -3100.0], [7260.0, -3110.0]], "type": "LineString"}, "id": 1890, "properties": {"stroke-width": 1}, "type": "Feature"}, {"geometry": {"coordinates": [[7260.0, -3110.0], [7260.0, -3120.0]], "type": "LineString"}, "id": 1891, "properties": {"stroke-width": 1}, "type": "Feature"}, {"geometry": {"coordinates": [[7260.0, -3120.0], [7270.0, -3120.0]], "type": "LineString"}, "id": 1892, "properties": {"stroke-width": 1}, "type": "Feature"}, {"geometry": {"coordinates": [[7270.0, -3120.0], [7270.0, -3130.0]], "type": "LineString"}, "id": 1893, "properties": {"stroke-width": 1}, "type": "Feature"}, {"geometry": {"coordinates": [[7270.0, -3130.0], [7270.0, -3140.0]], "type": "LineString"}, "id": 1894, "properties": {"stroke-width": 1}, "type": "Feature"}, {"geometry": {"coordinates": [[7270.0, -3140.0], [7270.0, -3150.0]], "type": "LineString"}, "id": 1895, "properties": {"stroke-width": 1}, "type": "Feature"}, {"geometry": {"coordinates": [[7270.0, -3150.0], [7280.0, -3150.0]], "type": "LineString"}, "id": 1896, "properties": {"stroke-width": 1}, "type": "Feature"}, {"geometry": {"coordinates": [[7280.0, -3150.0], [7280.0, -3160.0]], "type": "LineString"}, "id": 1897, "properties": {"stroke-width": 1}, "type": "Feature"}, {"geometry": {"coordinates": [[7280.0, -3160.0], [7280.0, -3170.0]], "type": "LineString"}, "id": 1898, "properties": {"stroke-width": 1}, "type": "Feature"}, {"geometry": {"coordinates": [[7280.0, -3170.0], [7280.0, -3180.0]], "type": "LineString"}, "id": 1899, "properties": {"stroke-width": 1}, "type": "Feature"}, {"geometry": {"coordinates": [[7280.0, -3180.0], [7280.0, -3190.0]], "type": "LineString"}, "id": 1900, "properties": {"stroke-width": 1}, "type": "Feature"}, {"geometry": {"coordinates": [[7280.0, -3190.0], [7280.0, -3200.0]], "type": "LineString"}, "id": 1901, "properties": {"stroke-width": 1}, "type": "Feature"}, {"geometry": {"coordinates": [[7280.0, -3200.0], [7290.0, -3200.0]], "type": "LineString"}, "id": 1902, "properties": {"stroke-width": 1}, "type": "Feature"}, {"geometry": {"coordinates": [[7290.0, -3200.0], [7290.0, -3210.0]], "type": "LineString"}, "id": 1903, "properties": {"stroke-width": 1}, "type": "Feature"}, {"geometry": {"coordinates": [[7290.0, -3210.0], [7300.0, -3210.0]], "type": "LineString"}, "id": 1904, "properties": {"stroke-width": 1}, "type": "Feature"}, {"geometry": {"coordinates": [[7300.0, -3210.0], [7300.0, -3220.0]], "type": "LineString"}, "id": 1905, "properties": {"stroke-width": 1}, "type": "Feature"}, {"geometry": {"coordinates": [[7300.0, -3220.0], [7300.0, -3230.0]], "type": "LineString"}, "id": 1906, "properties": {"stroke-width": 1}, "type": "Feature"}, {"geometry": {"coordinates": [[7300.0, -3230.0], [7300.0, -3240.0]], "type": "LineString"}, "id": 1907, "properties": {"stroke-width": 1}, "type": "Feature"}, {"geometry": {"coordinates": [[7300.0, -3240.0], [7310.0, -3240.0]], "type": "LineString"}, "id": 1908, "properties": {"stroke-width": 1}, "type": "Feature"}, {"geometry": {"coordinates": [[7310.0, -3240.0], [7310.0, -3250.0]], "type": "LineString"}, "id": 1909, "properties": {"stroke-width": 1}, "type": "Feature"}, {"geometry": {"coordinates": [[7310.0, -3250.0], [7320.0, -3250.0]], "type": "LineString"}, "id": 1910, "properties": {"stroke-width": 1}, "type": "Feature"}, {"geometry": {"coordinates": [[7320.0, -3250.0], [7320.0, -3260.0]], "type": "LineString"}, "id": 1911, "properties": {"stroke-width": 1}, "type": "Feature"}, {"geometry": {"coordinates": [[7320.0, -3260.0], [7320.0, -3270.0]], "type": "LineString"}, "id": 1912, "properties": {"stroke-width": 1}, "type": "Feature"}, {"geometry": {"coordinates": [[7320.0, -3270.0], [7320.0, -3280.0]], "type": "LineString"}, "id": 1913, "properties": {"stroke-width": 1}, "type": "Feature"}, {"geometry": {"coordinates": [[7320.0, -3280.0], [7320.0, -3290.0]], "type": "LineString"}, "id": 1914, "properties": {"stroke-width": 1}, "type": "Feature"}, {"geometry": {"coordinates": [[7320.0, -3290.0], [7320.0, -3300.0]], "type": "LineString"}, "id": 1915, "properties": {"stroke-width": 1}, "type": "Feature"}, {"geometry": {"coordinates": [[7320.0, -3300.0], [7320.0, -3310.0]], "type": "LineString"}, "id": 1916, "properties": {"stroke-width": 1}, "type": "Feature"}, {"geometry": {"coordinates": [[7320.0, -3310.0], [7320.0, -3320.0]], "type": "LineString"}, "id": 1917, "properties": {"stroke-width": 1}, "type": "Feature"}, {"geometry": {"coordinates": [[7320.0, -3320.0], [7320.0, -3330.0]], "type": "LineString"}, "id": 1918, "properties": {"stroke-width": 1}, "type": "Feature"}, {"geometry": {"coordinates": [[7320.0, -3330.0], [7320.0, -3340.0]], "type": "LineString"}, "id": 1919, "properties": {"stroke-width": 1}, "type": "Feature"}, {"geometry": {"coordinates": [[7320.0, -3340.0], [7320.0, -3350.0]], "type": "LineString"}, "id": 1920, "properties": {"stroke-width": 1}, "type": "Feature"}, {"geometry": {"coordinates": [[7320.0, -3350.0], [7320.0, -3360.0]], "type": "LineString"}, "id": 1921, "properties": {"stroke-width": 1}, "type": "Feature"}, {"geometry": {"coordinates": [[7320.0, -3360.0], [7320.0, -3370.0]], "type": "LineString"}, "id": 1922, "properties": {"stroke-width": 1}, "type": "Feature"}, {"geometry": {"coordinates": [[7320.0, -3370.0], [7330.0, -3370.0]], "type": "LineString"}, "id": 1923, "properties": {"stroke-width": 1}, "type": "Feature"}, {"geometry": {"coordinates": [[7330.0, -3370.0], [7340.0, -3370.0]], "type": "LineString"}, "id": 1924, "properties": {"stroke-width": 1}, "type": "Feature"}, {"geometry": {"coordinates": [[7340.0, -3370.0], [7350.0, -3370.0]], "type": "LineString"}, "id": 1925, "properties": {"stroke-width": 1}, "type": "Feature"}, {"geometry": {"coordinates": [[7350.0, -3370.0], [7360.0, -3370.0]], "type": "LineString"}, "id": 1926, "properties": {"stroke-width": 1}, "type": "Feature"}, {"geometry": {"coordinates": [[7360.0, -3370.0], [7370.0, -3370.0]], "type": "LineString"}, "id": 1927, "properties": {"stroke-width": 1}, "type": "Feature"}, {"geometry": {"coordinates": [[7370.0, -3370.0], [7370.0, -3380.0]], "type": "LineString"}, "id": 1928, "properties": {"stroke-width": 1}, "type": "Feature"}, {"geometry": {"coordinates": [[7370.0, -3380.0], [7370.0, -3390.0]], "type": "LineString"}, "id": 1929, "properties": {"stroke-width": 1}, "type": "Feature"}, {"geometry": {"coordinates": [[7370.0, -3390.0], [7370.0, -3400.0]], "type": "LineString"}, "id": 1930, "properties": {"stroke-width": 1}, "type": "Feature"}, {"geometry": {"coordinates": [[7370.0, -3400.0], [7370.0, -3400.0]], "type": "LineString"}, "id": 1931, "properties": {"stroke-width": 1}, "type": "Feature"}, {"geometry": {"coordinates": [[7530.0, -3560.0], [7530.0, -3560.0]], "type": "LineString"}, "id": 1965, "properties": {"stroke-width": 1}, "type": "Feature"}, {"geometry": {"coordinates": [[7530.0, -3560.0], [7540.0, -3560.0]], "type": "LineString"}, "id": 1966, "properties": {"stroke-width": 1}, "type": "Feature"}, {"geometry": {"coordinates": [[7540.0, -3560.0], [7550.0, -3560.0]], "type": "LineString"}, "id": 1967, "properties": {"stroke-width": 1}, "type": "Feature"}, {"geometry": {"coordinates": [[7550.0, -3560.0], [7550.0, -3570.0]], "type": "LineString"}, "id": 1968, "properties": {"stroke-width": 1}, "type": "Feature"}, {"geometry": {"coordinates": [[7550.0, -3570.0], [7550.0, -3570.0]], "type": "LineString"}, "id": 1969, "properties": {"stroke-width": 1}, "type": "Feature"}, {"geometry": {"coordinates": [[7720.0, -3650.0], [7720.0, -3650.0]], "type": "LineString"}, "id": 1997, "properties": {"stroke-width": 1}, "type": "Feature"}, {"geometry": {"coordinates": [[7720.0, -3650.0], [7730.0, -3650.0]], "type": "LineString"}, "id": 1998, "properties": {"stroke-width": 1}, "type": "Feature"}, {"geometry": {"coordinates": [[7730.0, -3650.0], [7740.0, -3650.0]], "type": "LineString"}, "id": 1999, "properties": {"stroke-width": 1}, "type": "Feature"}, {"geometry": {"coordinates": [[7740.0, -3650.0], [7740.0, -3660.0]], "type": "LineString"}, "id": 2000, "properties": {"stroke-width": 1}, "type": "Feature"}, {"geometry": {"coordinates": [[7740.0, -3660.0], [7750.0, -3660.0]], "type": "LineString"}, "id": 2001, "properties": {"stroke-width": 1}, "type": "Feature"}, {"geometry": {"coordinates": [[7750.0, -3660.0], [7760.0, -3660.0]], "type": "LineString"}, "id": 2002, "properties": {"stroke-width": 1}, "type": "Feature"}, {"geometry": {"coordinates": [[7760.0, -3660.0], [7770.0, -3660.0]], "type": "LineString"}, "id": 2003, "properties": {"stroke-width": 1}, "type": "Feature"}, {"geometry": {"coordinates": [[7770.0, -3660.0], [7770.0, -3670.0]], "type": "LineString"}, "id": 2004, "properties": {"stroke-width": 1}, "type": "Feature"}, {"geometry": {"coordinates": [[7770.0, -3670.0], [7780.0, -3670.0]], "type": "LineString"}, "id": 2005, "properties": {"stroke-width": 1}, "type": "Feature"}, {"geometry": {"coordinates": [[7780.0, -3670.0], [7790.0, -3670.0]], "type": "LineString"}, "id": 2006, "properties": {"stroke-width": 1}, "type": "Feature"}, {"geometry": {"coordinates": [[7790.0, -3670.0], [7800.0, -3670.0]], "type": "LineString"}, "id": 2007, "properties": {"stroke-width": 1}, "type": "Feature"}, {"geometry": {"coordinates": [[7800.0, -3670.0], [7810.0, -3670.0]], "type": "LineString"}, "id": 2008, "properties": {"stroke-width": 1}, "type": "Feature"}, {"geometry": {"coordinates": [[7810.0, -3670.0], [7820.0, -3670.0]], "type": "LineString"}, "id": 2009, "properties": {"stroke-width": 1}, "type": "Feature"}, {"geometry": {"coordinates": [[7820.0, -3670.0], [7830.0, -3670.0]], "type": "LineString"}, "id": 2010, "properties": {"stroke-width": 1}, "type": "Feature"}, {"geometry": {"coordinates": [[7830.0, -3670.0], [7840.0, -3670.0]], "type": "LineString"}, "id": 2011, "properties": {"stroke-width": 1}, "type": "Feature"}, {"geometry": {"coordinates": [[7840.0, -3670.0], [7840.0, -3660.0]], "type": "LineString"}, "id": 2012, "properties": {"stroke-width": 1}, "type": "Feature"}, {"geometry": {"coordinates": [[7840.0, -3660.0], [7850.0, -3660.0]], "type": "LineString"}, "id": 2013, "properties": {"stroke-width": 1}, "type": "Feature"}, {"geometry": {"coordinates": [[7850.0, -3660.0], [7850.0, -3650.0]], "type": "LineString"}, "id": 2014, "properties": {"stroke-width": 1}, "type": "Feature"}, {"geometry": {"coordinates": [[7850.0, -3650.0], [7850.0, -3640.0]], "type": "LineString"}, "id": 2015, "properties": {"stroke-width": 1}, "type": "Feature"}, {"geometry": {"coordinates": [[7850.0, -3640.0], [7850.0, -3630.0]], "type": "LineString"}, "id": 2016, "properties": {"stroke-width": 1}, "type": "Feature"}, {"geometry": {"coordinates": [[7850.0, -3630.0], [7850.0, -3620.0]], "type": "LineString"}, "id": 2017, "properties": {"stroke-width": 1}, "type": "Feature"}, {"geometry": {"coordinates": [[7850.0, -3620.0], [7850.0, -3610.0]], "type": "LineString"}, "id": 2018, "properties": {"stroke-width": 1}, "type": "Feature"}, {"geometry": {"coordinates": [[7850.0, -3610.0], [7850.0, -3600.0]], "type": "LineString"}, "id": 2019, "properties": {"stroke-width": 1}, "type": "Feature"}, {"geometry": {"coordinates": [[7850.0, -3600.0], [7860.0, -3600.0]], "type": "LineString"}, "id": 2020, "properties": {"stroke-width": 1}, "type": "Feature"}, {"geometry": {"coordinates": [[7860.0, -3600.0], [7870.0, -3600.0]], "type": "LineString"}, "id": 2021, "properties": {"stroke-width": 1}, "type": "Feature"}, {"geometry": {"coordinates": [[7870.0, -3600.0], [7870.0, -3600.0]], "type": "LineString"}, "id": 2022, "properties": {"stroke-width": 1}, "type": "Feature"}, {"geometry": {"coordinates": [[7880.0, -3640.0], [7880.0, -3640.0]], "type": "LineString"}, "id": 2028, "properties": {"stroke-width": 1}, "type": "Feature"}, {"geometry": {"coordinates": [[7880.0, -3640.0], [7880.0, -3650.0]], "type": "LineString"}, "id": 2029, "properties": {"stroke-width": 1}, "type": "Feature"}, {"geometry": {"coordinates": [[7880.0, -3650.0], [7890.0, -3650.0]], "type": "LineString"}, "id": 2030, "properties": {"stroke-width": 1}, "type": "Feature"}, {"geometry": {"coordinates": [[7890.0, -3650.0], [7890.0, -3660.0]], "type": "LineString"}, "id": 2031, "properties": {"stroke-width": 1}, "type": "Feature"}, {"geometry": {"coordinates": [[7890.0, -3660.0], [7890.0, -3670.0]], "type": "LineString"}, "id": 2032, "properties": {"stroke-width": 1}, "type": "Feature"}, {"geometry": {"coordinates": [[7890.0, -3670.0], [7890.0, -3680.0]], "type": "LineString"}, "id": 2033, "properties": {"stroke-width": 1}, "type": "Feature"}, {"geometry": {"coordinates": [[7890.0, -3680.0], [7890.0, -3690.0]], "type": "LineString"}, "id": 2034, "properties": {"stroke-width": 1}, "type": "Feature"}, {"geometry": {"coordinates": [[7890.0, -3690.0], [7890.0, -3700.0]], "type": "LineString"}, "id": 2035, "properties": {"stroke-width": 1}, "type": "Feature"}, {"geometry": {"coordinates": [[7890.0, -3700.0], [7890.0, -3700.0]], "type": "LineString"}, "id": 2036, "properties": {"stroke-width": 1}, "type": "Feature"}, {"geometry": {"coordinates": [[7340.0, -4380.0], [7340.0, -4380.0]], "type": "LineString"}, "id": 3080, "properties": {"stroke-width": 1}, "type": "Feature"}, {"geometry": {"coordinates": [[7340.0, -4380.0], [7340.0, -4380.0]], "type": "LineString"}, "id": 3081, "properties": {"stroke-width": 1}, "type": "Feature"}, {"geometry": {"coordinates": [[7790.0, -3750.0], [7790.0, -3750.0]], "type": "LineString"}, "id": 3451, "properties": {"stroke-width": 1}, "type": "Feature"}, {"geometry": {"coordinates": [[8140.0, -3930.0], [8140.0, -3930.0]], "type": "LineString"}, "id": 3495, "properties": {"stroke-width": 1}, "type": "Feature"}, {"geometry": {"coordinates": [[8140.0, -3930.0], [8150.0, -3930.0]], "type": "LineString"}, "id": 3496, "properties": {"stroke-width": 1}, "type": "Feature"}, {"geometry": {"coordinates": [[8150.0, -3930.0], [8160.0, -3930.0]], "type": "LineString"}, "id": 3497, "properties": {"stroke-width": 1}, "type": "Feature"}, {"geometry": {"coordinates": [[8160.0, -3930.0], [8160.0, -3930.0]], "type": "LineString"}, "id": 3498, "properties": {"stroke-width": 1}, "type": "Feature"}, {"geometry": {"coordinates": [[7980.0, -3780.0], [7980.0, -3780.0]], "type": "LineString"}, "id": 3644, "properties": {"stroke-width": 1}, "type": "Feature"}, {"geometry": {"coordinates": [[7980.0, -3780.0], [7990.0, -3780.0]], "type": "LineString"}, "id": 3645, "properties": {"stroke-width": 1}, "type": "Feature"}, {"geometry": {"coordinates": [[7990.0, -3780.0], [7990.0, -3770.0]], "type": "LineString"}, "id": 3646, "properties": {"stroke-width": 1}, "type": "Feature"}, {"geometry": {"coordinates": [[7990.0, -3770.0], [8000.0, -3770.0]], "type": "LineString"}, "id": 3647, "properties": {"stroke-width": 1}, "type": "Feature"}, {"geometry": {"coordinates": [[8000.0, -3770.0], [8000.0, -3760.0]], "type": "LineString"}, "id": 3648, "properties": {"stroke-width": 1}, "type": "Feature"}, {"geometry": {"coordinates": [[8000.0, -3760.0], [8010.0, -3760.0]], "type": "LineString"}, "id": 3649, "properties": {"stroke-width": 1}, "type": "Feature"}, {"geometry": {"coordinates": [[8000.0, -3340.0], [8000.0, -3340.0]], "type": "LineString"}, "id": 3759, "properties": {"stroke-width": 1}, "type": "Feature"}, {"geometry": {"coordinates": [[8000.0, -3340.0], [8000.0, -3340.0]], "type": "LineString"}, "id": 3760, "properties": {"stroke-width": 1}, "type": "Feature"}, {"geometry": {"coordinates": [[8020.0, -3760.0], [8020.0, -3760.0]], "type": "LineString"}, "id": 4526, "properties": {"stroke-width": 1}, "type": "Feature"}, {"geometry": {"coordinates": [[7860.0, -3600.0], [7860.0, -3600.0]], "type": "LineString"}, "id": 4560, "properties": {"stroke-width": 1}, "type": "Feature"}, {"geometry": {"coordinates": [[8490.0, -3660.0], [8490.0, -3660.0]], "type": "LineString"}, "id": 4754, "properties": {"stroke-width": 1}, "type": "Feature"}, {"geometry": {"coordinates": [[8490.0, -3660.0], [8500.0, -3660.0]], "type": "LineString"}, "id": 4755, "properties": {"stroke-width": 1}, "type": "Feature"}, {"geometry": {"coordinates": [[8500.0, -3660.0], [8500.0, -3660.0]], "type": "LineString"}, "id": 4756, "properties": {"stroke-width": 1}, "type": "Feature"}, {"geometry": {"coordinates": [[8480.0, -3660.0], [8480.0, -3660.0]], "type": "LineString"}, "id": 4823, "properties": {"stroke-width": 1}, "type": "Feature"}, {"geometry": {"coordinates": [[8480.0, -3660.0], [8480.0, -3660.0]], "type": "LineString"}, "id": 4824, "properties": {"stroke-width": 1}, "type": "Feature"}, {"geometry": {"coordinates": [[8590.0, -3980.0], [8590.0, -3980.0]], "type": "LineString"}, "id": 4887, "properties": {"stroke-width": 1}, "type": "Feature"}, {"geometry": {"coordinates": [[8590.0, -3980.0], [8590.0, -3980.0]], "type": "LineString"}, "id": 4888, "properties": {"stroke-width": 1}, "type": "Feature"}, {"geometry": {"coordinates": [[8530.0, -3930.0], [8530.0, -3930.0]], "type": "LineString"}, "id": 4918, "properties": {"stroke-width": 1}, "type": "Feature"}, {"geometry": {"coordinates": [[8530.0, -3930.0], [8530.0, -3930.0]], "type": "LineString"}, "id": 4919, "properties": {"stroke-width": 1}, "type": "Feature"}, {"geometry": {"coordinates": [[8420.0, -3950.0], [8420.0, -3950.0]], "type": "LineString"}, "id": 4969, "properties": {"stroke-width": 1}, "type": "Feature"}, {"geometry": {"coordinates": [[8420.0, -3950.0], [8420.0, -3950.0]], "type": "LineString"}, "id": 4970, "properties": {"stroke-width": 1}, "type": "Feature"}, {"geometry": {"coordinates": [[7550.0, -3570.0], [7560.0, -3570.0]], "type": "LineString"}, "id": 5078, "properties": {"stroke-width": 1}, "type": "Feature"}, {"geometry": {"coordinates": [[7560.0, -3570.0], [7560.0, -3580.0]], "type": "LineString"}, "id": 5079, "properties": {"stroke-width": 1}, "type": "Feature"}, {"geometry": {"coordinates": [[7560.0, -3580.0], [7560.0, -3580.0]], "type": "LineString"}, "id": 5080, "properties": {"stroke-width": 1}, "type": "Feature"}, {"geometry": {"coordinates": [[7330.0, -4100.0], [7330.0, -4100.0]], "type": "LineString"}, "id": 12673, "properties": {"stroke-width": 1}, "type": "Feature"}, {"geometry": {"coordinates": [[7330.0, -4100.0], [7340.0, -4100.0]], "type": "LineString"}, "id": 12674, "properties": {"stroke-width": 1}, "type": "Feature"}, {"geometry": {"coordinates": [[7340.0, -4100.0], [7350.0, -4100.0]], "type": "LineString"}, "id": 12675, "properties": {"stroke-width": 1}, "type": "Feature"}, {"geometry": {"coordinates": [[7350.0, -4100.0], [7350.0, -4110.0]], "type": "LineString"}, "id": 12676, "properties": {"stroke-width": 1}, "type": "Feature"}, {"geometry": {"coordinates": [[7350.0, -4110.0], [7350.0, -4110.0]], "type": "LineString"}, "id": 12677, "properties": {"stroke-width": 1}, "type": "Feature"}, {"geometry": {"coordinates": [[7430.0, -3790.0], [7430.0, -3790.0]], "type": "LineString"}, "id": 12774, "properties": {"stroke-width": 1}, "type": "Feature"}, {"geometry": {"coordinates": [[7430.0, -3790.0], [7420.0, -3790.0]], "type": "LineString"}, "id": 12775, "properties": {"stroke-width": 1}, "type": "Feature"}, {"geometry": {"coordinates": [[7420.0, -3790.0], [7420.0, -3790.0]], "type": "LineString"}, "id": 12776, "properties": {"stroke-width": 1}, "type": "Feature"}, {"geometry": {"coordinates": [[7310.0, -3240.0], [7320.0, -3240.0]], "type": "LineString"}, "id": 12972, "properties": {"stroke-width": 1}, "type": "Feature"}, {"geometry": {"coordinates": [[7320.0, -3240.0], [7330.0, -3240.0]], "type": "LineString"}, "id": 12973, "properties": {"stroke-width": 1}, "type": "Feature"}, {"geometry": {"coordinates": [[7330.0, -3240.0], [7340.0, -3240.0]], "type": "LineString"}, "id": 12974, "properties": {"stroke-width": 1}, "type": "Feature"}, {"geometry": {"coordinates": [[7340.0, -3240.0], [7350.0, -3240.0]], "type": "LineString"}, "id": 12975, "properties": {"stroke-width": 1}, "type": "Feature"}, {"geometry": {"coordinates": [[7350.0, -3240.0], [7350.0, -3250.0]], "type": "LineString"}, "id": 12976, "properties": {"stroke-width": 1}, "type": "Feature"}, {"geometry": {"coordinates": [[7350.0, -3250.0], [7350.0, -3260.0]], "type": "LineString"}, "id": 12977, "properties": {"stroke-width": 1}, "type": "Feature"}, {"geometry": {"coordinates": [[7350.0, -3260.0], [7350.0, -3270.0]], "type": "LineString"}, "id": 12978, "properties": {"stroke-width": 1}, "type": "Feature"}, {"geometry": {"coordinates": [[7350.0, -3270.0], [7360.0, -3270.0]], "type": "LineString"}, "id": 12979, "properties": {"stroke-width": 1}, "type": "Feature"}, {"geometry": {"coordinates": [[7360.0, -3270.0], [7360.0, -3280.0]], "type": "LineString"}, "id": 12980, "properties": {"stroke-width": 1}, "type": "Feature"}, {"geometry": {"coordinates": [[7360.0, -3280.0], [7370.0, -3280.0]], "type": "LineString"}, "id": 12981, "properties": {"stroke-width": 1}, "type": "Feature"}, {"geometry": {"coordinates": [[7370.0, -3280.0], [7380.0, -3280.0]], "type": "LineString"}, "id": 12982, "properties": {"stroke-width": 1}, "type": "Feature"}, {"geometry": {"coordinates": [[7380.0, -3280.0], [7390.0, -3280.0]], "type": "LineString"}, "id": 12983, "properties": {"stroke-width": 1}, "type": "Feature"}, {"geometry": {"coordinates": [[7390.0, -3280.0], [7400.0, -3280.0]], "type": "LineString"}, "id": 12984, "properties": {"stroke-width": 1}, "type": "Feature"}, {"geometry": {"coordinates": [[7400.0, -3280.0], [7400.0, -3280.0]], "type": "LineString"}, "id": 12985, "properties": {"stroke-width": 1}, "type": "Feature"}, {"geometry": {"coordinates": [[7600.0, -3320.0], [7600.0, -3320.0]], "type": "LineString"}, "id": 13022, "properties": {"stroke-width": 1}, "type": "Feature"}, {"geometry": {"coordinates": [[7600.0, -3320.0], [7600.0, -3320.0]], "type": "LineString"}, "id": 13023, "properties": {"stroke-width": 1}, "type": "Feature"}, {"geometry": {"coordinates": [[7750.0, -3340.0], [7750.0, -3340.0]], "type": "LineString"}, "id": 13074, "properties": {"stroke-width": 1}, "type": "Feature"}, {"geometry": {"coordinates": [[7750.0, -3340.0], [7750.0, -3340.0]], "type": "LineString"}, "id": 13075, "properties": {"stroke-width": 1}, "type": "Feature"}, {"geometry": {"coordinates": [[7960.0, -3180.0], [7960.0, -3180.0]], "type": "LineString"}, "id": 13168, "properties": {"stroke-width": 1}, "type": "Feature"}, {"geometry": {"coordinates": [[7960.0, -3180.0], [7970.0, -3180.0]], "type": "LineString"}, "id": 13169, "properties": {"stroke-width": 1}, "type": "Feature"}, {"geometry": {"coordinates": [[7970.0, -3180.0], [7970.0, -3190.0]], "type": "LineString"}, "id": 13170, "properties": {"stroke-width": 1}, "type": "Feature"}, {"geometry": {"coordinates": [[7970.0, -3190.0], [7980.0, -3190.0]], "type": "LineString"}, "id": 13171, "properties": {"stroke-width": 1}, "type": "Feature"}, {"geometry": {"coordinates": [[7980.0, -3190.0], [7990.0, -3190.0]], "type": "LineString"}, "id": 13172, "properties": {"stroke-width": 1}, "type": "Feature"}, {"geometry": {"coordinates": [[7990.0, -3190.0], [8000.0, -3190.0]], "type": "LineString"}, "id": 13173, "properties": {"stroke-width": 1}, "type": "Feature"}, {"geometry": {"coordinates": [[8000.0, -3190.0], [8010.0, -3190.0]], "type": "LineString"}, "id": 13174, "properties": {"stroke-width": 1}, "type": "Feature"}, {"geometry": {"coordinates": [[8010.0, -3190.0], [8020.0, -3190.0]], "type": "LineString"}, "id": 13175, "properties": {"stroke-width": 1}, "type": "Feature"}, {"geometry": {"coordinates": [[8020.0, -3190.0], [8030.0, -3190.0]], "type": "LineString"}, "id": 13176, "properties": {"stroke-width": 1}, "type": "Feature"}, {"geometry": {"coordinates": [[8030.0, -3190.0], [8030.0, -3200.0]], "type": "LineString"}, "id": 13177, "properties": {"stroke-width": 1}, "type": "Feature"}, {"geometry": {"coordinates": [[8030.0, -3200.0], [8030.0, -3210.0]], "type": "LineString"}, "id": 13178, "properties": {"stroke-width": 1}, "type": "Feature"}, {"geometry": {"coordinates": [[8030.0, -3210.0], [8020.0, -3210.0]], "type": "LineString"}, "id": 13179, "properties": {"stroke-width": 1}, "type": "Feature"}, {"geometry": {"coordinates": [[8020.0, -3210.0], [8020.0, -3220.0]], "type": "LineString"}, "id": 13180, "properties": {"stroke-width": 1}, "type": "Feature"}, {"geometry": {"coordinates": [[8020.0, -3220.0], [8020.0, -3230.0]], "type": "LineString"}, "id": 13181, "properties": {"stroke-width": 1}, "type": "Feature"}, {"geometry": {"coordinates": [[8020.0, -3230.0], [8020.0, -3240.0]], "type": "LineString"}, "id": 13182, "properties": {"stroke-width": 1}, "type": "Feature"}, {"geometry": {"coordinates": [[8020.0, -3240.0], [8020.0, -3240.0]], "type": "LineString"}, "id": 13183, "properties": {"stroke-width": 1}, "type": "Feature"}, {"geometry": {"coordinates": [[8100.0, -3290.0], [8100.0, -3290.0]], "type": "LineString"}, "id": 13199, "properties": {"stroke-width": 1}, "type": "Feature"}, {"geometry": {"coordinates": [[8100.0, -3290.0], [8110.0, -3290.0]], "type": "LineString"}, "id": 13200, "properties": {"stroke-width": 1}, "type": "Feature"}, {"geometry": {"coordinates": [[8110.0, -3290.0], [8110.0, -3300.0]], "type": "LineString"}, "id": 13201, "properties": {"stroke-width": 1}, "type": "Feature"}, {"geometry": {"coordinates": [[8110.0, -3300.0], [8120.0, -3300.0]], "type": "LineString"}, "id": 13202, "properties": {"stroke-width": 1}, "type": "Feature"}, {"geometry": {"coordinates": [[8120.0, -3300.0], [8130.0, -3300.0]], "type": "LineString"}, "id": 13203, "properties": {"stroke-width": 1}, "type": "Feature"}, {"geometry": {"coordinates": [[8130.0, -3300.0], [8130.0, -3310.0]], "type": "LineString"}, "id": 13204, "properties": {"stroke-width": 1}, "type": "Feature"}, {"geometry": {"coordinates": [[8130.0, -3310.0], [8130.0, -3320.0]], "type": "LineString"}, "id": 13205, "properties": {"stroke-width": 1}, "type": "Feature"}, {"geometry": {"coordinates": [[8130.0, -3320.0], [8140.0, -3320.0]], "type": "LineString"}, "id": 13206, "properties": {"stroke-width": 1}, "type": "Feature"}, {"geometry": {"coordinates": [[8140.0, -3320.0], [8150.0, -3320.0]], "type": "LineString"}, "id": 13207, "properties": {"stroke-width": 1}, "type": "Feature"}, {"geometry": {"coordinates": [[8150.0, -3320.0], [8150.0, -3330.0]], "type": "LineString"}, "id": 13208, "properties": {"stroke-width": 1}, "type": "Feature"}, {"geometry": {"coordinates": [[8150.0, -3330.0], [8160.0, -3330.0]], "type": "LineString"}, "id": 13209, "properties": {"stroke-width": 1}, "type": "Feature"}, {"geometry": {"coordinates": [[8160.0, -3330.0], [8160.0, -3340.0]], "type": "LineString"}, "id": 13210, "properties": {"stroke-width": 1}, "type": "Feature"}, {"geometry": {"coordinates": [[8160.0, -3340.0], [8160.0, -3340.0]], "type": "LineString"}, "id": 13211, "properties": {"stroke-width": 1}, "type": "Feature"}, {"geometry": {"coordinates": [[8290.0, -3400.0], [8290.0, -3400.0]], "type": "LineString"}, "id": 13241, "properties": {"stroke-width": 1}, "type": "Feature"}, {"geometry": {"coordinates": [[8290.0, -3400.0], [8290.0, -3390.0]], "type": "LineString"}, "id": 13242, "properties": {"stroke-width": 1}, "type": "Feature"}, {"geometry": {"coordinates": [[8290.0, -3390.0], [8290.0, -3380.0]], "type": "LineString"}, "id": 13243, "properties": {"stroke-width": 1}, "type": "Feature"}, {"geometry": {"coordinates": [[8290.0, -3380.0], [8280.0, -3380.0]], "type": "LineString"}, "id": 13244, "properties": {"stroke-width": 1}, "type": "Feature"}, {"geometry": {"coordinates": [[8280.0, -3380.0], [8270.0, -3380.0]], "type": "LineString"}, "id": 13245, "properties": {"stroke-width": 1}, "type": "Feature"}, {"geometry": {"coordinates": [[8270.0, -3380.0], [8270.0, -3370.0]], "type": "LineString"}, "id": 13246, "properties": {"stroke-width": 1}, "type": "Feature"}, {"geometry": {"coordinates": [[8270.0, -3370.0], [8270.0, -3360.0]], "type": "LineString"}, "id": 13247, "properties": {"stroke-width": 1}, "type": "Feature"}, {"geometry": {"coordinates": [[8270.0, -3360.0], [8280.0, -3360.0]], "type": "LineString"}, "id": 13248, "properties": {"stroke-width": 1}, "type": "Feature"}, {"geometry": {"coordinates": [[8280.0, -3360.0], [8290.0, -3360.0]], "type": "LineString"}, "id": 13249, "properties": {"stroke-width": 1}, "type": "Feature"}, {"geometry": {"coordinates": [[8290.0, -3360.0], [8300.0, -3360.0]], "type": "LineString"}, "id": 13250, "properties": {"stroke-width": 1}, "type": "Feature"}, {"geometry": {"coordinates": [[8300.0, -3360.0], [8300.0, -3360.0]], "type": "LineString"}, "id": 13251, "properties": {"stroke-width": 1}, "type": "Feature"}, {"geometry": {"coordinates": [[7280.0, -3200.0], [7280.0, -3200.0]], "type": "LineString"}, "id": 13443, "properties": {"stroke-width": 1}, "type": "Feature"}, {"geometry": {"coordinates": [[6970.0, -3120.0], [6970.0, -3120.0]], "type": "LineString"}, "id": 13493, "properties": {"stroke-width": 1}, "type": "Feature"}, {"geometry": {"coordinates": [[6970.0, -3120.0], [6970.0, -3130.0]], "type": "LineString"}, "id": 13494, "properties": {"stroke-width": 1}, "type": "Feature"}, {"geometry": {"coordinates": [[6970.0, -3130.0], [6980.0, -3130.0]], "type": "LineString"}, "id": 13495, "properties": {"stroke-width": 1}, "type": "Feature"}, {"geometry": {"coordinates": [[6980.0, -3130.0], [6980.0, -3140.0]], "type": "LineString"}, "id": 13496, "properties": {"stroke-width": 1}, "type": "Feature"}, {"geometry": {"coordinates": [[6980.0, -3140.0], [6980.0, -3150.0]], "type": "LineString"}, "id": 13497, "properties": {"stroke-width": 1}, "type": "Feature"}, {"geometry": {"coordinates": [[6980.0, -3150.0], [6980.0, -3160.0]], "type": "LineString"}, "id": 13498, "properties": {"stroke-width": 1}, "type": "Feature"}, {"geometry": {"coordinates": [[6980.0, -3160.0], [6990.0, -3160.0]], "type": "LineString"}, "id": 13499, "properties": {"stroke-width": 1}, "type": "Feature"}, {"geometry": {"coordinates": [[6990.0, -3160.0], [6990.0, -3160.0]], "type": "LineString"}, "id": 13500, "properties": {"stroke-width": 1}, "type": "Feature"}, {"geometry": {"coordinates": [[6890.0, -3190.0], [6890.0, -3190.0]], "type": "LineString"}, "id": 13554, "properties": {"stroke-width": 1}, "type": "Feature"}, {"geometry": {"coordinates": [[6890.0, -3190.0], [6880.0, -3190.0]], "type": "LineString"}, "id": 13555, "properties": {"stroke-width": 1}, "type": "Feature"}, {"geometry": {"coordinates": [[6880.0, -3190.0], [6880.0, -3190.0]], "type": "LineString"}, "id": 13556, "properties": {"stroke-width": 1}, "type": "Feature"}, {"geometry": {"coordinates": [[6640.0, -2600.0], [6640.0, -2600.0]], "type": "LineString"}, "id": 13657, "properties": {"stroke-width": 1}, "type": "Feature"}, {"geometry": {"coordinates": [[6640.0, -2600.0], [6630.0, -2600.0]], "type": "LineString"}, "id": 13658, "properties": {"stroke-width": 1}, "type": "Feature"}, {"geometry": {"coordinates": [[6630.0, -2600.0], [6630.0, -2610.0]], "type": "LineString"}, "id": 13659, "properties": {"stroke-width": 1}, "type": "Feature"}, {"geometry": {"coordinates": [[6630.0, -2610.0], [6630.0, -2620.0]], "type": "LineString"}, "id": 13660, "properties": {"stroke-width": 1}, "type": "Feature"}, {"geometry": {"coordinates": [[6630.0, -2620.0], [6620.0, -2620.0]], "type": "LineString"}, "id": 13661, "properties": {"stroke-width": 1}, "type": "Feature"}, {"geometry": {"coordinates": [[6620.0, -2620.0], [6620.0, -2630.0]], "type": "LineString"}, "id": 13662, "properties": {"stroke-width": 1}, "type": "Feature"}, {"geometry": {"coordinates": [[6620.0, -2630.0], [6610.0, -2630.0]], "type": "LineString"}, "id": 13663, "properties": {"stroke-width": 1}, "type": "Feature"}, {"geometry": {"coordinates": [[6610.0, -2630.0], [6610.0, -2640.0]], "type": "LineString"}, "id": 13664, "properties": {"stroke-width": 1}, "type": "Feature"}, {"geometry": {"coordinates": [[6610.0, -2640.0], [6600.0, -2640.0]], "type": "LineString"}, "id": 13665, "properties": {"stroke-width": 1}, "type": "Feature"}, {"geometry": {"coordinates": [[6600.0, -2640.0], [6600.0, -2650.0]], "type": "LineString"}, "id": 13666, "properties": {"stroke-width": 1}, "type": "Feature"}, {"geometry": {"coordinates": [[6600.0, -2650.0], [6600.0, -2650.0]], "type": "LineString"}, "id": 13667, "properties": {"stroke-width": 1}, "type": "Feature"}, {"geometry": {"coordinates": [[6370.0, -2730.0], [6370.0, -2730.0]], "type": "LineString"}, "id": 13701, "properties": {"stroke-width": 1}, "type": "Feature"}, {"geometry": {"coordinates": [[6370.0, -2730.0], [6360.0, -2730.0]], "type": "LineString"}, "id": 13702, "properties": {"stroke-width": 1}, "type": "Feature"}, {"geometry": {"coordinates": [[6360.0, -2730.0], [6350.0, -2730.0]], "type": "LineString"}, "id": 13703, "properties": {"stroke-width": 1}, "type": "Feature"}, {"geometry": {"coordinates": [[6350.0, -2730.0], [6350.0, -2740.0]], "type": "LineString"}, "id": 13704, "properties": {"stroke-width": 1}, "type": "Feature"}, {"geometry": {"coordinates": [[6350.0, -2740.0], [6340.0, -2740.0]], "type": "LineString"}, "id": 13705, "properties": {"stroke-width": 1}, "type": "Feature"}, {"geometry": {"coordinates": [[6340.0, -2740.0], [6340.0, -2740.0]], "type": "LineString"}, "id": 13706, "properties": {"stroke-width": 1}, "type": "Feature"}, {"geometry": {"coordinates": [[4460.0, -2680.0], [4460.0, -2680.0]], "type": "LineString"}, "id": 14043, "properties": {"stroke-width": 1}, "type": "Feature"}, {"geometry": {"coordinates": [[4460.0, -2680.0], [4450.0, -2680.0]], "type": "LineString"}, "id": 14044, "properties": {"stroke-width": 1}, "type": "Feature"}, {"geometry": {"coordinates": [[4450.0, -2680.0], [4440.0, -2680.0]], "type": "LineString"}, "id": 14045, "properties": {"stroke-width": 1}, "type": "Feature"}, {"geometry": {"coordinates": [[4440.0, -2680.0], [4440.0, -2680.0]], "type": "LineString"}, "id": 14046, "properties": {"stroke-width": 1}, "type": "Feature"}, {"geometry": {"coordinates": [[4310.0, -2700.0], [4310.0, -2700.0]], "type": "LineString"}, "id": 14064, "properties": {"stroke-width": 1}, "type": "Feature"}, {"geometry": {"coordinates": [[4310.0, -2700.0], [4310.0, -2690.0]], "type": "LineString"}, "id": 14065, "properties": {"stroke-width": 1}, "type": "Feature"}, {"geometry": {"coordinates": [[4310.0, -2690.0], [4310.0, -2690.0]], "type": "LineString"}, "id": 14066, "properties": {"stroke-width": 1}, "type": "Feature"}, {"geometry": {"coordinates": [[4200.0, -2630.0], [4200.0, -2630.0]], "type": "LineString"}, "id": 14094, "properties": {"stroke-width": 1}, "type": "Feature"}, {"geometry": {"coordinates": [[4200.0, -2630.0], [4190.0, -2630.0]], "type": "LineString"}, "id": 14095, "properties": {"stroke-width": 1}, "type": "Feature"}, {"geometry": {"coordinates": [[4190.0, -2630.0], [4190.0, -2640.0]], "type": "LineString"}, "id": 14096, "properties": {"stroke-width": 1}, "type": "Feature"}, {"geometry": {"coordinates": [[4190.0, -2640.0], [4180.0, -2640.0]], "type": "LineString"}, "id": 14097, "properties": {"stroke-width": 1}, "type": "Feature"}, {"geometry": {"coordinates": [[4180.0, -2640.0], [4180.0, -2650.0]], "type": "LineString"}, "id": 14098, "properties": {"stroke-width": 1}, "type": "Feature"}, {"geometry": {"coordinates": [[4180.0, -2650.0], [4180.0, -2660.0]], "type": "LineString"}, "id": 14099, "properties": {"stroke-width": 1}, "type": "Feature"}, {"geometry": {"coordinates": [[4180.0, -2660.0], [4170.0, -2660.0]], "type": "LineString"}, "id": 14100, "properties": {"stroke-width": 1}, "type": "Feature"}, {"geometry": {"coordinates": [[4170.0, -2660.0], [4170.0, -2660.0]], "type": "LineString"}, "id": 14101, "properties": {"stroke-width": 1}, "type": "Feature"}, {"geometry": {"coordinates": [[4390.0, -1390.0], [4390.0, -1390.0]], "type": "LineString"}, "id": 14624, "properties": {"stroke-width": 1}, "type": "Feature"}, {"geometry": {"coordinates": [[4390.0, -1390.0], [4390.0, -1380.0]], "type": "LineString"}, "id": 14625, "properties": {"stroke-width": 1}, "type": "Feature"}, {"geometry": {"coordinates": [[4390.0, -1380.0], [4380.0, -1380.0]], "type": "LineString"}, "id": 14626, "properties": {"stroke-width": 1}, "type": "Feature"}, {"geometry": {"coordinates": [[4380.0, -1380.0], [4370.0, -1380.0]], "type": "LineString"}, "id": 14627, "properties": {"stroke-width": 1}, "type": "Feature"}, {"geometry": {"coordinates": [[4370.0, -1380.0], [4370.0, -1370.0]], "type": "LineString"}, "id": 14628, "properties": {"stroke-width": 1}, "type": "Feature"}, {"geometry": {"coordinates": [[4370.0, -1370.0], [4370.0, -1370.0]], "type": "LineString"}, "id": 14629, "properties": {"stroke-width": 1}, "type": "Feature"}, {"geometry": {"coordinates": [[4460.0, -2670.0], [4460.0, -2670.0]], "type": "LineString"}, "id": 15100, "properties": {"stroke-width": 1}, "type": "Feature"}, {"geometry": {"coordinates": [[4460.0, -2670.0], [4470.0, -2670.0]], "type": "LineString"}, "id": 15101, "properties": {"stroke-width": 1}, "type": "Feature"}, {"geometry": {"coordinates": [[4470.0, -2670.0], [4480.0, -2670.0]], "type": "LineString"}, "id": 15102, "properties": {"stroke-width": 1}, "type": "Feature"}, {"geometry": {"coordinates": [[4480.0, -2670.0], [4490.0, -2670.0]], "type": "LineString"}, "id": 15103, "properties": {"stroke-width": 1}, "type": "Feature"}, {"geometry": {"coordinates": [[4490.0, -2670.0], [4500.0, -2670.0]], "type": "LineString"}, "id": 15104, "properties": {"stroke-width": 1}, "type": "Feature"}, {"geometry": {"coordinates": [[4500.0, -2670.0], [4500.0, -2670.0]], "type": "LineString"}, "id": 15105, "properties": {"stroke-width": 1}, "type": "Feature"}, {"geometry": {"coordinates": [[4600.0, -2820.0], [4600.0, -2820.0]], "type": "LineString"}, "id": 15133, "properties": {"stroke-width": 1}, "type": "Feature"}, {"geometry": {"coordinates": [[4600.0, -2820.0], [4600.0, -2820.0]], "type": "LineString"}, "id": 15134, "properties": {"stroke-width": 1}, "type": "Feature"}, {"geometry": {"coordinates": [[7000.0, -2230.0], [7000.0, -2230.0]], "type": "LineString"}, "id": 15936, "properties": {"stroke-width": 1}, "type": "Feature"}, {"geometry": {"coordinates": [[7000.0, -2230.0], [7000.0, -2230.0]], "type": "LineString"}, "id": 15937, "properties": {"stroke-width": 1}, "type": "Feature"}, {"geometry": {"coordinates": [[7580.0, -2280.0], [7580.0, -2280.0]], "type": "LineString"}, "id": 16434, "properties": {"stroke-width": 1}, "type": "Feature"}, {"geometry": {"coordinates": [[7580.0, -2280.0], [7580.0, -2280.0]], "type": "LineString"}, "id": 16435, "properties": {"stroke-width": 1}, "type": "Feature"}, {"geometry": {"coordinates": [[7180.0, -2170.0], [7180.0, -2170.0]], "type": "LineString"}, "id": 16550, "properties": {"stroke-width": 1}, "type": "Feature"}, {"geometry": {"coordinates": [[7180.0, -2170.0], [7180.0, -2170.0]], "type": "LineString"}, "id": 16551, "properties": {"stroke-width": 1}, "type": "Feature"}], "type": "FeatureCollection"}